uranium/__init__.py
uranium/app_globals.py
uranium/build.py
uranium/config.py
uranium/decorators.py
uranium/environment_variables.py
uranium/exceptions.py
uranium/executables.py
uranium/experimental.py
uranium/history.py
uranium/hooks.py
uranium/main.py
uranium/options.py
uranium/proxy.py
uranium/remote.py
uranium/tasks.py
uranium/lib/__init__.py
uranium/lib/asserts.py
uranium/lib/context.py
uranium/lib/log_templates.py
uranium/lib/script_runner.py
uranium/lib/utils.py
uranium/lib/compat/__init__.py
uranium/lib/sandbox/__init__.py
uranium/lib/sandbox/venv/__init__.py
uranium/lib/sandbox/venv/activate.py
uranium/lib/sandbox/venv/activate_this.py
uranium/lib/sandbox/venv/utils.py
uranium/packages/__init__.py
uranium/packages/pippuppet.py
uranium/packages/versions.py
uranium/rules/__init__.py
uranium/rules/base.py
uranium/rules/once.py
uranium/rules/was_changed.py
uranium/scripts/__init__.py
uranium/scripts/activate_this.py
uranium/tests/__init__.py
uranium/tests/conftest.py
uranium/tests/test_app_globals.py
uranium/tests/test_app_globals_full.py
uranium/tests/test_config.py
uranium/tests/test_executables.py
uranium/tests/test_executables_full.py
uranium/tests/test_exit_codes.py
uranium/tests/test_get_remote_script_full.py
uranium/tests/test_history.py
uranium/tests/test_history_full.py
uranium/tests/test_hooks_full.py
uranium/tests/test_logging_full.py
uranium/tests/test_options_full.py
uranium/tests/test_packages_full.py
uranium/tests/test_tasks_full.py
uranium/tests/test_uranium_script.py
uranium/tests/test_uranium_standalone.py
uranium/tests/decorators/__init__.py
uranium/tests/decorators/test_task_requires.py
uranium/tests/lib/__init__.py
uranium/tests/lib/test_context.py
uranium/tests/packages/__init__.py
uranium/tests/packages/test_versions.py
uranium/tests/rules/__init__.py
uranium/tests/rules/test_once.py
uranium/tests/rules/test_rules.py
uranium/tests/rules/test_was_changed.py
uranium/tests/tasks/__init__.py
uranium/tests/tasks/test_tasks.py
uranium-2.1.2.dist-info/LICENSE
uranium-2.1.2.dist-info/METADATA
uranium-2.1.2.dist-info/WHEEL
uranium-2.1.2.dist-info/entry_points.txt
uranium-2.1.2.dist-info/top_level.txt
uranium-2.1.2.dist-info/RECORD
