Metadata-Version: 2.1
Name: uranium
Version: 2.1.2
Summary: a build system for python
Home-page: http://uranium.readthedocs.org
Author: Yusuke Tsutsumi
Author-email: yusuke@tsutsumi.io
License: UNKNOWN
Platform: UNKNOWN
Classifier: Development Status :: 4 - Beta
Classifier: Operating System :: MacOS
Classifier: Operating System :: POSIX :: Linux
Classifier: Topic :: System :: Software Distribution
Classifier: License :: OSI Approved :: MIT License
Classifier: Programming Language :: Python
Classifier: Programming Language :: Python :: 2
Classifier: Programming Language :: Python :: 3
Requires-Dist: coloredlogs (==10.0)
Requires-Dist: deepmerge (==0.0.4)
Requires-Dist: docopt (==0.6.2)
Requires-Dist: packaging (>=19.0)
Requires-Dist: pip (>=19.2.3)
Requires-Dist: requests (==2.22.0)
Requires-Dist: setuptools (>=41.2.0)
Requires-Dist: virtualenv (==16.6.0)
